arycal-0.2.1.data/scripts/arycal
arycal-0.2.1.dist-info/METADATA
arycal-0.2.1.dist-info/WHEEL
arycal/__init__.py
arycal-0.2.1.dist-info/RECORD
