Metadata-Version: 2.4
Name: arycal
Version: 0.2.1
Classifier: Development Status :: 4 - Beta
Classifier: Intended Audience :: Science/Research
Classifier: License :: OSI Approved :: MIT License
Classifier: Programming Language :: Python :: 3
Classifier: Programming Language :: Python :: 3.8
Classifier: Programming Language :: Python :: 3.9
Classifier: Programming Language :: Python :: 3.10
Classifier: Programming Language :: Python :: 3.11
Classifier: Programming Language :: Python :: 3.12
Classifier: Programming Language :: Rust
Classifier: Topic :: Scientific/Engineering :: Bio-Informatics
Summary: Across Run dYnamic Chromatogram ALignment - A Rust-based tool for aligning extracted ion chromatograms (EICs) across multiple runs
Keywords: mass-spectrometry,chromatogram,alignment,bioinformatics,proteomics
Author-email: Justin Sing <justincsing@gmail.com>
License: MIT
Requires-Python: >=3.8
Project-URL: Homepage, https://github.com/singjc/arycal
Project-URL: Repository, https://github.com/singjc/arycal
Project-URL: Documentation, https://github.com/singjc/arycal
